Half_Add/half_add.v
/*
half adder module
Auther: R Ansh Joseph
Date: Oct7 2023
Time: 8:35PM
*/
module half_adder(bit1,bit2,sum,carry);
    input bit1,bit2;
    output carry,sum;
    xor  G1 (sum,bit1,bit2);
    and  G2 (carry,bit1,bit2);
endmodule

Full_Add/full_adder.v
/*
Auther: R Ansh Joseph
Date: Oct 8 2023
version: 0.0.1
Module: Full Adder
Dependency: Half Adder
*/
`include "../Half_Add/half_add.v"

module full_adder(bit1,bit2,cbit,sum,carry);
    input bit1,bit2,cbit;
    output sum,carry;

    wire inter1_sum,inter1_carry;
    half_adder M1(bit1,bit2,inter1_sum,inter1_carry);
    half_adder M2(inter1_sum,cbit,sum,carry);
endmodule

Full_Add/full_adder_tb.v
/*
Auther: R Ansh Joseph
Date: Oct 8 2023
version: 0.0.1
Module: Full Adder Test banch
Dependency: Half Adder, Full Adder
*/
`include "./full_adder.v"

module full_adder_test_banch;
    reg bit1,bit2,cbit;
    wire sum,carry;
    full_adder M1(bit1,bit2,cbit,sum,carry);
    initial begin
      $dumpfile("full_adder.vcd");
      $dumpvars(0,full_adder_test_banch);

      bit1=0;bit2=0;cbit=0;
      #1
      bit1=0;bit2=0;cbit=1;
      #1
      bit1=0;bit2=1;cbit=0;
      #1
      bit1=0;bit2=1;cbit=1;
      #1
      bit1=1;bit2=0;cbit=0;
      #1
      bit1=1;bit2=0;cbit=1;
      #1
      bit1=1;bit2=1;cbit=0;
      #1
      bit1=1;bit2=1;cbit=1;
    end

endmodule

Full_Add/full_adder.vcd
$date
	Sun Oct  8 10:56:44 2023
$end
$version
	Icarus Verilog
$end
$timescale
	1s
$end
$scope module full_adder_test_banch $end
$var wire 1 ! sum $end
$var wire 1 " carry $end
$var reg 1 # bit1 $end
$var reg 1 $ bit2 $end
$var reg 1 % cbit $end
$scope module M1 $end
$var wire 1 # bit1 $end
$var wire 1 $ bit2 $end
$var wire 1 % cbit $end
$var wire 1 ! sum $end
$var wire 1 & inter1_sum $end
$var wire 1 ' inter1_carry $end
$var wire 1 " carry $end
$scope module M1 $end
$var wire 1 # bit1 $end
$var wire 1 $ bit2 $end
$var wire 1 ' carry $end
$var wire 1 & sum $end
$upscope $end
$scope module M2 $end
$var wire 1 & bit1 $end
$var wire 1 % bit2 $end
$var wire 1 " carry $end
$var wire 1 ! sum $end
$upscope $end
$upscope $end
$upscope $end
$enddefinitions $end
#0
$dumpvars
0'
0&
0%
0$
0#
0"
0!
$end
#1
1!
1%
#2
1&
0%
1$
#3
0!
1"
1%
#4
1!
0"
0%
0$
1#
#5
0!
1"
1%
#6
0"
0&
1'
0%
1$
#7
1!
1%
